miniRV_pipeline_axi_ego1/src/rtl/defines.vh
// -----------------------------------------------------------------------------
// 全工程公共控制码和地址映射
// -----------------------------------------------------------------------------
// RUN_TRACE 只在课程 Trace 仿真时由编译命令打开。下板 CoreMark 必须保持关闭，
// 否则会绕过多周期乘除法，得到与 FPGA 实现不一致的时序模型。
// `define RUN_TRACE

// 最终 Cache 构建：I/D Cache 均为 64-line direct-mapped、16-byte line。
// 关闭任一宏仍可回到无 Cache 调试路径，用于隔离 AXI 或 Cache 问题。
`define ENABLE_ICACHE
`define ENABLE_DCACHE

`define IC_LINE_COUNT 64
`define DC_LINE_COUNT 64
// 只有片上普通存储区参与缓存；所有 0xFFFF_xxxx MMIO 必须 Uncached。
`define CACHEABLE_LIMIT 32'h0008_0000

// 复位后第一条取指地址。
`define PC_INIT_VAL 32'h0

// ALU 功能码：Controller 译码产生，EX 级送入 ALU。
`define ALU_ADD     5'h00
`define ALU_SUB     5'h01
`define ALU_OR      5'h03
`define ALU_XOR     5'h04
`define ALU_SLL     5'h05
`define ALU_SRL     5'h06
`define ALU_SRA     5'h07
`define ALU_EQ      5'h08
`define ALU_NE      5'h09
`define ALU_AND     5'h0A
`define ALU_SLT     5'h0B
`define ALU_SLTU    5'h0C
`define ALU_MUL     5'h0D
`define ALU_DIV     5'h0E
`define ALU_REM     5'h0F
`define ALU_LT      5'h10
`define ALU_GE      5'h11
`define ALU_LTU     5'h12
`define ALU_GEU     5'h13
`define ALU_MULH    5'h14
`define ALU_MULHU   5'h15
`define ALU_DIVU    5'h16
`define ALU_REMU    5'h17

// 下一 PC 类型：顺序 PC+4、JALR、条件分支、JAL。
`define NPC_PC4     2'b00
`define NPC_JALR    2'b01
`define NPC_BRA     2'b10
`define NPC_JMP     2'b11

// 五类 RISC-V 立即数编码，由 SEXT 使用。
`define EXT_I       3'b000
`define EXT_S       3'b001
`define EXT_B       3'b010
`define EXT_U       3'b011
`define EXT_J       3'b100

// WB 写回数据来源：ALU、内存、PC+4、U 型立即数。
`define WB_ALU      2'b00
`define WB_RAM      2'b01
`define WB_PC4      2'b10
`define WB_EXT      2'b11

// EX 级 ALU A/B 端输入选择。
`define ALU_A_RS1   1'b0
`define ALU_A_PC    1'b1

`define ALU_B_RS2   1'b0
`define ALU_B_EXT   1'b1

// Load 数据扩展类型：不读、整字、有/无符号字节、有/无符号半字。
`define RAM_EXT_N   3'b000
`define RAM_EXT_W   3'b001
`define RAM_EXT_B   3'b010
`define RAM_EXT_BU  3'b011
`define RAM_EXT_H   3'b100
`define RAM_EXT_HU  3'b101

// Store 基础字节使能；MREQ 再根据地址低两位移动到正确 byte lane。
`define RAM_WE_N    4'b0000
`define RAM_WE_B    4'b0001
`define RAM_WE_H    4'b0011
`define RAM_WE_W    4'b1111

// 地址空间。最终 EGO1 版实际片上 BRAM 为 150 KiB，板级模块还会进一步做边界判断。
`define MEM_BLOCK_MEMORY    32'h0000_0000   // 512KB (0x0000_0000 ~ 0x0007_FFFF)
`define MEM_DDR3            32'h2000_0000   // 512MB (0x2000_0000 ~ 0x3FFF_FFFF)
`define PERI_ADDR_SWITCH    32'hFFFF_0000
`define PERI_ADDR_LED       32'hFFFF_1000
`define PERI_ADDR_DIGLED    32'hFFFF_2000
`define PERI_ADDR_UART      32'hFFFF_3000
`define PERI_ADDR_TIMER     32'hFFFF_4000

// Cache 关闭时，一次总线请求只传一个 32 位字；打开时一条 line 为 4 words。
`ifdef ENABLE_ICACHE
    `define IC_BLK_LEN  4
    `define IC_BLK_SIZE (`IC_BLK_LEN*32)
`else
    `define IC_BLK_LEN  1
    `define IC_BLK_SIZE (`IC_BLK_LEN*32)
`endif

`ifdef ENABLE_DCACHE
    `define DC_BLK_LEN  4
    `define DC_BLK_SIZE (`DC_BLK_LEN*32)
`else
    `define DC_BLK_LEN  1
    `define DC_BLK_SIZE (`DC_BLK_LEN*32)
`endif

miniRV_pipeline_axi_ego1/src/rtl/axi_master.v
`timescale 1ns / 1ps

`include "defines.vh"

// -----------------------------------------------------------------------------
// 无 Cache、单未决事务 AXI4 Master
// -----------------------------------------------------------------------------
// CPU 侧有取指读、数据读、数据写三个简单请求口，本模块把它们转换为 AXI 五通道。
// 仲裁优先级：data write > data read > instruction read。
// 每次均为对齐的 32-bit 单拍传输；SB/SH 通过 WSTRB 选择有效 byte lane。
// “请求有效”不等于“事务完成”：只有 VALID && READY 的上升沿才完成对应通道握手。
module axi_master(
    // 与 CPU/板级 Slave 同一个 50 MHz 时钟域；areset 高有效同步复位。
    input  wire         aclk,
    input  wire         areset,     // high active

    // CPU 取指侧：rrdy 表示 Master 此刻愿意接收请求，rvalid 是返回脉冲。
    output reg          ic_dev_rrdy,
    input  wire         ic_cpu_ren,
    input  wire [31:0]  ic_cpu_raddr,
    output reg          ic_dev_rvalid,
    output reg  [`IC_BLK_SIZE-1:0] ic_dev_rdata,

    // CPU 数据写侧：wen 同时是请求存在标志和 4-bit 字节写使能。
    output reg          dc_dev_wrdy,
    input  wire [ 3:0]  dc_cpu_wen,
    input  wire [31:0]  dc_cpu_waddr,
    input  wire [31:0]  dc_cpu_wdata,
    output reg          dc_dev_wresp,

    // CPU 数据读侧。
    output reg          dc_dev_rrdy,
    input  wire         dc_cpu_ren,
    input  wire [31:0]  dc_cpu_raddr,
    output reg          dc_dev_rvalid,
    output reg  [`DC_BLK_SIZE-1:0] dc_dev_rdata,

    // AXI 写地址通道 AW。
    output reg  [31:0]  m_axi_awaddr,
    output wire [ 7:0]  m_axi_awlen,
    output wire [ 2:0]  m_axi_awsize,
    output wire [ 1:0]  m_axi_awburst,
    output reg          m_axi_awvalid,
    input  wire         m_axi_awready,

    // AXI 写数据通道 W；地址和数据通道互相独立，可在不同拍握手。
    output reg  [31:0]  m_axi_wdata,
    output reg  [ 3:0]  m_axi_wstrb,
    output wire         m_axi_wlast,
    output reg          m_axi_wvalid,
    input  wire         m_axi_wready,

    // AXI 写响应通道 B；收到响应后才向 CPU 发 dc_dev_wresp。
    output reg          m_axi_bready,
    input  wire [ 1:0]  m_axi_bresp,
    input  wire         m_axi_bvalid,

    // AXI 读地址通道 AR。
    output reg  [31:0]  m_axi_araddr,
    output wire [ 7:0]  m_axi_arlen,
    output wire [ 2:0]  m_axi_arsize,
    output wire [ 1:0]  m_axi_arburst,
    output reg          m_axi_arvalid,
    input  wire         m_axi_arready,

    // AXI 读数据通道 R；read_is_data 决定返回给取指口还是数据口。
    output reg          m_axi_rready,
    input  wire [31:0]  m_axi_rdata,
    input  wire [ 1:0]  m_axi_rresp,
    input  wire         m_axi_rlast,
    input  wire         m_axi_rvalid
);

    // 五态 FSM：
    // IDLE 等 CPU 请求；RADDR 等 AR 握手；RDATA 等 R 握手；
    // WSEND 独立等待 AW/W 都完成；WRESP 等 B 响应。
    localparam [2:0] ST_IDLE   = 3'd0;
    localparam [2:0] ST_RADDR  = 3'd1;
    localparam [2:0] ST_RDATA  = 3'd2;
    localparam [2:0] ST_WSEND  = 3'd3;
    localparam [2:0] ST_WRESP  = 3'd4;

    reg [2:0] state;
    // 锁存当前读事务来源，因为到 RDATA 时原始 CPU 请求可能已变化。
    reg       read_is_data;

    // 当前实现固定为 1 beat、每 beat 4 bytes、INCR burst。
    assign m_axi_awlen   = 8'd0;
    assign m_axi_awsize  = 3'b010; // four bytes per beat
    assign m_axi_awburst = 2'b01;  // INCR
    assign m_axi_wlast   = 1'b1;
    assign m_axi_arlen   = 8'd0;
    assign m_axi_arsize  = 3'b010;
    assign m_axi_arburst = 2'b01;

    // CPU 侧组合 ready 仲裁。只有 IDLE 才接收新事务；重叠请求时只有最高优先级
    // 接口看到 ready=1，避免同拍接受两个请求。
    always @(*) begin
        ic_dev_rrdy = 1'b0;
        dc_dev_rrdy = 1'b0;
        dc_dev_wrdy = 1'b0;

        if (state == ST_IDLE) begin
            // 写口默认最高优先；无写时才开放数据读；两者都无请求才开放取指。
            dc_dev_wrdy = 1'b1;
            dc_dev_rrdy = !(|dc_cpu_wen);
            ic_dev_rrdy = !(|dc_cpu_wen) && !dc_cpu_ren;
        end
    end

    // sys_rst 在 PLL lock 后仍保持若干拍。这里使用同步复位，避免驱动 BRAM 的
    // AXI 地址/控制寄存器触发 Vivado REQP-1839。
    always @(posedge aclk) begin
        if (areset) begin
            state           <= ST_IDLE;
            read_is_data    <= 1'b0;
            ic_dev_rvalid   <= 1'b0;
            ic_dev_rdata    <= {`IC_BLK_SIZE{1'b0}};
            dc_dev_rvalid   <= 1'b0;
            dc_dev_rdata    <= {`DC_BLK_SIZE{1'b0}};
            dc_dev_wresp    <= 1'b0;
            m_axi_awaddr    <= 32'h0;
            m_axi_awvalid   <= 1'b0;
            m_axi_wdata     <= 32'h0;
            m_axi_wstrb     <= 4'h0;
            m_axi_wvalid    <= 1'b0;
            m_axi_bready    <= 1'b0;
            m_axi_araddr    <= 32'h0;
            m_axi_arvalid   <= 1'b0;
            m_axi_rready    <= 1'b0;
        end else begin
            // CPU 侧响应默认每拍清零，因此都是单周期 pulse，防止 core 把同一响应
            // 当成两次完成事件。
            ic_dev_rvalid <= 1'b0;
            dc_dev_rvalid <= 1'b0;
            dc_dev_wresp  <= 1'b0;

            case (state)
                ST_IDLE: begin
                    // 接受数据写：锁存对齐地址、数据和 WSTRB，同时拉高 AWVALID/WVALID。
                    if ((|dc_cpu_wen) && dc_dev_wrdy) begin
                        m_axi_awaddr  <= {dc_cpu_waddr[31:2], 2'b00};
                        m_axi_awvalid <= 1'b1;
                        m_axi_wdata   <= dc_cpu_wdata;
                        m_axi_wstrb   <= dc_cpu_wen;
                        m_axi_wvalid  <= 1'b1;
                        state         <= ST_WSEND;
                    end else if (dc_cpu_ren && dc_dev_rrdy) begin
                        // 接受数据读并记住返回目标。
                        read_is_data  <= 1'b1;
                        m_axi_araddr  <= {dc_cpu_raddr[31:2], 2'b00};
                        m_axi_arvalid <= 1'b1;
                        state         <= ST_RADDR;
                    end else if (ic_cpu_ren && ic_dev_rrdy) begin
                        // 接受取指读；与数据读共用 AR/R 通道。
                        read_is_data  <= 1'b0;
                        m_axi_araddr  <= {ic_cpu_raddr[31:2], 2'b00};
                        m_axi_arvalid <= 1'b1;
                        state         <= ST_RADDR;
                    end
                end

                ST_RADDR: begin
                    // ARVALID 必须保持，直到 Slave 用 ARREADY 接受地址。
                    if (m_axi_arvalid && m_axi_arready) begin
                        m_axi_arvalid <= 1'b0;
                        m_axi_rready  <= 1'b1;
                        state         <= ST_RDATA;
                    end
                end

                ST_RDATA: begin
                    // RVALID && RREADY 才消费数据。按 read_is_data 路由并产生 CPU pulse。
                    if (m_axi_rvalid && m_axi_rready) begin
                        m_axi_rready <= 1'b0;
                        if (read_is_data) begin
                            dc_dev_rdata  <= m_axi_rdata;
                            dc_dev_rvalid <= 1'b1;
                        end else begin
                            ic_dev_rdata  <= m_axi_rdata;
                            ic_dev_rvalid <= 1'b1;
                        end
                        state <= ST_IDLE;
                    end
                end

                ST_WSEND: begin
                    // AW 和 W 可独立完成，各自握手后只清自己的 VALID。
                    if (m_axi_awvalid && m_axi_awready)
                        m_axi_awvalid <= 1'b0;
                    if (m_axi_wvalid && m_axi_wready)
                        m_axi_wvalid <= 1'b0;

                    // 当前拍之后两通道都已完成时，开始等待写响应。
                    if ((!m_axi_awvalid || m_axi_awready) &&
                        (!m_axi_wvalid  || m_axi_wready)) begin
                        m_axi_bready <= 1'b1;
                        state        <= ST_WRESP;
                    end
                end

                ST_WRESP: begin
                    // B 通道确认整个写事务完成，再向 CPU 发单拍 wresp。
                    if (m_axi_bvalid && m_axi_bready) begin
                        m_axi_bready <= 1'b0;
                        dc_dev_wresp <= 1'b1;
                        state        <= ST_IDLE;
                    end
                end

                default: state <= ST_IDLE;
            endcase
        end
    end

    // 当前 CPU 简单接口没有异常返回通道，因此 BRESP/RRESP/RLAST 不影响功能；
    // 保留引用以消除综合未使用告警，AXI testbench 仍会检查它们。
    wire _unused_ok = &{1'b0, m_axi_bresp, m_axi_rresp, m_axi_rlast};

endmodule

miniRV_pipeline_axi_ego1/tests/axi_master_tb.v
`timescale 1ns / 1ps

module axi_master_tb;
    reg clk = 1'b0;
    always #5 clk = !clk;

`ifdef DUMP_VCD
    initial begin
        $dumpfile("06_no_cache_axi_transaction.vcd");
        $dumpvars(0, axi_master_tb);
    end
`endif

    reg rst = 1'b1;
    reg ic_req = 1'b0;
    reg [31:0] ic_addr = 32'h0;
    wire ic_ready;
    wire ic_valid;
    wire [31:0] ic_data;
    reg dc_read = 1'b0;
    reg [31:0] dc_addr = 32'h0;
    wire dc_read_ready;
    wire dc_valid;
    wire [31:0] dc_data;
    reg [3:0] dc_wen = 4'h0;
    reg [31:0] dc_waddr = 32'h0;
    reg [31:0] dc_wdata = 32'h0;
    wire dc_write_ready;
    wire dc_write_resp;

    wire [31:0] awaddr;
    wire [7:0] awlen;
    wire [2:0] awsize;
    wire [1:0] awburst;
    wire awvalid;
    reg awready = 1'b0;
    wire [31:0] wdata;
    wire [3:0] wstrb;
    wire wlast;
    wire wvalid;
    reg wready = 1'b0;
    wire bready;
    reg [1:0] bresp = 2'b00;
    reg bvalid = 1'b0;
    wire [31:0] araddr;
    wire [7:0] arlen;
    wire [2:0] arsize;
    wire [1:0] arburst;
    wire arvalid;
    reg arready = 1'b0;
    wire rready;
    reg [31:0] rdata = 32'h0;
    reg [1:0] rresp = 2'b00;
    reg rlast = 1'b1;
    reg rvalid = 1'b0;

    axi_master dut (
        .aclk(clk), .areset(rst),
        .ic_dev_rrdy(ic_ready), .ic_cpu_ren(ic_req), .ic_cpu_raddr(ic_addr),
        .ic_dev_rvalid(ic_valid), .ic_dev_rdata(ic_data),
        .dc_dev_wrdy(dc_write_ready), .dc_cpu_wen(dc_wen),
        .dc_cpu_waddr(dc_waddr), .dc_cpu_wdata(dc_wdata),
        .dc_dev_wresp(dc_write_resp),
        .dc_dev_rrdy(dc_read_ready), .dc_cpu_ren(dc_read),
        .dc_cpu_raddr(dc_addr), .dc_dev_rvalid(dc_valid),
        .dc_dev_rdata(dc_data),
        .m_axi_awaddr(awaddr), .m_axi_awlen(awlen),
        .m_axi_awsize(awsize), .m_axi_awburst(awburst),
        .m_axi_awvalid(awvalid), .m_axi_awready(awready),
        .m_axi_wdata(wdata), .m_axi_wstrb(wstrb),
        .m_axi_wlast(wlast), .m_axi_wvalid(wvalid),
        .m_axi_wready(wready), .m_axi_bready(bready),
        .m_axi_bresp(bresp), .m_axi_bvalid(bvalid),
        .m_axi_araddr(araddr), .m_axi_arlen(arlen),
        .m_axi_arsize(arsize), .m_axi_arburst(arburst),
        .m_axi_arvalid(arvalid), .m_axi_arready(arready),
        .m_axi_rready(rready), .m_axi_rdata(rdata),
        .m_axi_rresp(rresp), .m_axi_rlast(rlast),
        .m_axi_rvalid(rvalid)
    );

    task fail;
        input [8*96-1:0] message;
        begin
            $fatal(1, "FAIL: %0s", message);
        end
    endtask

    initial begin
        repeat (3) @(posedge clk);
        rst <= 1'b0;

        // Instruction read: aligned address and stable valid under pressure.
        @(posedge clk); ic_addr <= 32'h0000_0003; ic_req <= 1'b1;
        @(posedge clk); ic_req <= 1'b0;
        repeat (2) @(posedge clk);
        if (!arvalid || araddr != 32'h0000_0000 ||
            arlen != 0 || arsize != 3'b010)
            fail("instruction AR channel");
        arready <= 1'b1;
        @(posedge clk); arready <= 1'b0;
        @(posedge clk); rdata <= 32'h1234_5678; rvalid <= 1'b1;
        @(posedge clk); rvalid <= 1'b0;
        #1;
        if (!ic_valid || ic_data != 32'h1234_5678)
            fail("instruction R response");

        // A data read must win over a simultaneous instruction request.
        @(posedge clk); dc_addr <= 32'h0000_0012; dc_read <= 1'b1;
                        ic_addr <= 32'h0000_0040; ic_req <= 1'b1;
        @(posedge clk); dc_read <= 1'b0; ic_req <= 1'b0;
        #1;
        if (araddr != 32'h0000_0010)
            fail("data-read priority/alignment");
        arready <= 1'b1;
        @(posedge clk); arready <= 1'b0;
        rdata <= 32'ha5a5_5a5a; rvalid <= 1'b1;
        @(posedge clk); rvalid <= 1'b0;
        #1;
        if (!dc_valid || dc_data != 32'ha5a5_5a5a)
            fail("data R response");

        // AW and W can complete independently; WSTRB must remain stable.
        @(posedge clk);
        dc_waddr <= 32'h0000_0023;
        dc_wdata <= 32'hdead_beef;
        dc_wen <= 4'b1000;
        @(posedge clk); dc_wen <= 4'h0;
        #1;
        if (!awvalid || !wvalid || awaddr != 32'h20 ||
            wstrb != 4'b1000 || !wlast)
            fail("write launch");
        awready <= 1'b1;
        @(posedge clk); awready <= 1'b0;
        #1;
        if (awvalid || !wvalid)
            fail("independent AW handshake");
        repeat (2) @(posedge clk);
        if (!wvalid || wdata != 32'hdead_beef || wstrb != 4'b1000)
            fail("W channel changed under backpressure");
        wready <= 1'b1;
        @(posedge clk); wready <= 1'b0;
        @(posedge clk); bvalid <= 1'b1;
        @(posedge clk); bvalid <= 1'b0;
        #1;
        if (!dc_write_resp)
            fail("write response");

        $display("PASS: axi_master_tb");
        $finish;
    end
endmodule

docs/course-report/vcd/06_no_cache_axi_transaction.vcd
$date
	Wed Jul 29 11:14:43 2026
$end
$version
	Icarus Verilog
$end
$timescale
	1ps
$end
$scope module axi_master_tb $end
$var wire 2 ! arburst [1:0] $end
$var wire 8 " arlen [7:0] $end
$var wire 3 # arsize [2:0] $end
$var wire 2 $ awburst [1:0] $end
$var wire 8 % awlen [7:0] $end
$var wire 3 & awsize [2:0] $end
$var wire 1 ' wlast $end
$var wire 1 ( wvalid $end
$var wire 4 ) wstrb [3:0] $end
$var wire 32 * wdata [31:0] $end
$var wire 1 + rready $end
$var wire 1 , ic_valid $end
$var wire 1 - ic_ready $end
$var wire 32 . ic_data [31:0] $end
$var wire 1 / dc_write_resp $end
$var wire 1 0 dc_write_ready $end
$var wire 1 1 dc_valid $end
$var wire 1 2 dc_read_ready $end
$var wire 32 3 dc_data [31:0] $end
$var wire 1 4 bready $end
$var wire 1 5 awvalid $end
$var wire 32 6 awaddr [31:0] $end
$var wire 1 7 arvalid $end
$var wire 32 8 araddr [31:0] $end
$var reg 1 9 arready $end
$var reg 1 : awready $end
$var reg 2 ; bresp [1:0] $end
$var reg 1 < bvalid $end
$var reg 1 = clk $end
$var reg 32 > dc_addr [31:0] $end
$var reg 1 ? dc_read $end
$var reg 32 @ dc_waddr [31:0] $end
$var reg 32 A dc_wdata [31:0] $end
$var reg 4 B dc_wen [3:0] $end
$var reg 32 C ic_addr [31:0] $end
$var reg 1 D ic_req $end
$var reg 32 E rdata [31:0] $end
$var reg 1 F rlast $end
$var reg 2 G rresp [1:0] $end
$var reg 1 H rst $end
$var reg 1 I rvalid $end
$var reg 1 J wready $end
$scope module dut $end
$var wire 1 = aclk $end
$var wire 1 H areset $end
$var wire 32 K dc_cpu_raddr [31:0] $end
$var wire 1 ? dc_cpu_ren $end
$var wire 32 L dc_cpu_waddr [31:0] $end
$var wire 32 M dc_cpu_wdata [31:0] $end
$var wire 4 N dc_cpu_wen [3:0] $end
$var wire 32 O ic_cpu_raddr [31:0] $end
$var wire 1 D ic_cpu_ren $end
$var wire 2 P m_axi_arburst [1:0] $end
$var wire 8 Q m_axi_arlen [7:0] $end
$var wire 1 9 m_axi_arready $end
$var wire 3 R m_axi_arsize [2:0] $end
$var wire 2 S m_axi_awburst [1:0] $end
$var wire 8 T m_axi_awlen [7:0] $end
$var wire 1 : m_axi_awready $end
$var wire 3 U m_axi_awsize [2:0] $end
$var wire 2 V m_axi_bresp [1:0] $end
$var wire 1 < m_axi_bvalid $end
$var wire 32 W m_axi_rdata [31:0] $end
$var wire 1 F m_axi_rlast $end
$var wire 2 X m_axi_rresp [1:0] $end
$var wire 1 I m_axi_rvalid $end
$var wire 1 ' m_axi_wlast $end
$var wire 1 J m_axi_wready $end
$var wire 1 Y _unused_ok $end
$var parameter 3 Z ST_IDLE $end
$var parameter 3 [ ST_RADDR $end
$var parameter 3 \ ST_RDATA $end
$var parameter 3 ] ST_WRESP $end
$var parameter 3 ^ ST_WSEND $end
$var reg 32 _ dc_dev_rdata [31:0] $end
$var reg 1 2 dc_dev_rrdy $end
$var reg 1 1 dc_dev_rvalid $end
$var reg 1 0 dc_dev_wrdy $end
$var reg 1 / dc_dev_wresp $end
$var reg 32 ` ic_dev_rdata [31:0] $end
$var reg 1 - ic_dev_rrdy $end
$var reg 1 , ic_dev_rvalid $end
$var reg 32 a m_axi_araddr [31:0] $end
$var reg 1 7 m_axi_arvalid $end
$var reg 32 b m_axi_awaddr [31:0] $end
$var reg 1 5 m_axi_awvalid $end
$var reg 1 4 m_axi_bready $end
$var reg 1 + m_axi_rready $end
$var reg 32 c m_axi_wdata [31:0] $end
$var reg 4 d m_axi_wstrb [3:0] $end
$var reg 1 ( m_axi_wvalid $end
$var reg 1 e read_is_data $end
$var reg 3 f state [2:0] $end
$upscope $end
$scope task fail $end
$var reg 768 g message [767:0] $end
$upscope $end
$upscope $end
$enddefinitions $end
$comment Show the parameter values. $end
$dumpall
b11 ^
b100 ]
b10 \
b1 [
b0 Z
$end
#0
$dumpvars
bx g
bx f
xe
bx d
bx c
bx b
bx a
bx `
bx _
0Y
b0 X
b0 W
b0 V
b10 U
b0 T
b1 S
b10 R
b0 Q
b1 P
b0 O
b0 N
b0 M
b0 L
b0 K
0J
0I
1H
b0 G
1F
b0 E
0D
b0 C
b0 B
b0 A
b0 @
0?
b0 >
0=
0<
b0 ;
0:
09
bx 8
x7
bx 6
x5
x4
bx 3
x2
x1
x0
x/
bx .
x-
x,
x+
bx *
bx )
x(
1'
b10 &
b0 %
b1 $
b10 #
b0 "
b1 !
$end
#5000
10
12
1-
0+
07
b0 8
b0 a
04
0(
b0 )
b0 d
b0 *
b0 c
05
b0 6
b0 b
0/
b0 3
b0 _
01
b0 .
b0 `
0,
0e
b0 f
1=
#10000
0=
#15000
1=
#20000
0=
#25000
0H
1=
#30000
0=
#35000
1D
b11 C
b11 O
1=
#40000
0=
#45000
00
02
0-
b1 f
17
0D
1=
#50000
0=
#55000
1=
#60000
0=
#65000
19
1=
#70000
0=
#75000
09
b10 f
1+
07
1=
#80000
0=
#85000
1I
b10010001101000101011001111000 E
b10010001101000101011001111000 W
1=
#90000
0=
#95000
1-
12
10
0I
b0 f
1,
b10010001101000101011001111000 .
b10010001101000101011001111000 `
0+
1=
#100000
0=
#105000
10
12
0-
0,
1D
b1000000 C
b1000000 O
1?
b10010 >
b10010 K
1=
#110000
0=
#115000
00
02
0D
0?
b1 f
17
b10000 8
b10000 a
1e
1=
#116000
19
#120000
0=
#125000
b10 f
1+
07
1I
b10100101101001010101101001011010 E
b10100101101001010101101001011010 W
09
1=
#130000
0=
#135000
1-
12
10
0I
b0 f
11
b10100101101001010101101001011010 3
b10100101101001010101101001011010 _
0+
1=
#140000
0=
#145000
10
02
0-
01
b1000 B
b1000 N
b11011110101011011011111011101111 A
b11011110101011011011111011101111 M
b100011 @
b100011 L
1=
#150000
0=
#155000
00
b0 B
b0 N
b11 f
1(
b1000 )
b1000 d
b11011110101011011011111011101111 *
b11011110101011011011111011101111 c
15
b100000 6
b100000 b
1=
#156000
1:
#160000
0=
#165000
05
0:
1=
#170000
0=
#175000
1=
#180000
0=
#185000
1J
1=
#190000
0=
#195000
b100 f
14
0(
0J
1=
#200000
0=
#205000
1<
1=
#210000
0=
#215000
1-
12
10
b0 f
1/
04
0<
1=
